focusedconv/README.md
focusedconv/__init__.py
focusedconv/areaofinterest.py
focusedconv/convolution.py
focusedconv-1.0.1.dist-info/METADATA
focusedconv-1.0.1.dist-info/WHEEL
focusedconv-1.0.1.dist-info/licenses/LICENSE
focusedconv-1.0.1.dist-info/RECORD
