Metadata-Version: 2.1
Name: focusedconv
Version: 1.0.1
Summary: Official library for the energy-efficient Focused Convolution
Project-URL: Homepage, https://github.com/calebtung/focused-convolutions
Project-URL: Bug Tracker, https://github.com/calebtung/focused-convolutions/issues
Author-email: Caleb Tung <tung3@purdue.edu>
License-File: LICENSE
Classifier: License :: OSI Approved :: Apache Software License
Classifier: Operating System :: OS Independent
Classifier: Programming Language :: Python :: 3
Requires-Python: >=3.7
Requires-Dist: matplotlib>=3
Requires-Dist: scikit-image>=0.18
Requires-Dist: torch>=1.12
